syntheticdb/__init__.py
syntheticdb/db_core.py
syntheticdb/distributions.py
syntheticdb/main.py
syntheticdb/query_parser.py
syntheticdb-0.0.19.dist-info/WHEEL
syntheticdb-0.0.19.dist-info/METADATA
syntheticdb-0.0.19.dist-info/RECORD
