Metadata-Version: 2.1
Name: syntheticdb
Version: 0.0.19
Summary: 
License: MIT
Requires-Python: >=3.7.1,<4.0
Classifier: License :: OSI Approved :: MIT License
Classifier: Programming Language :: Python :: 3
Classifier: Programming Language :: Python :: 3.8
Classifier: Programming Language :: Python :: 3.9
Requires-Dist: matplotlib (>=3)
Requires-Dist: pandas (>=1)
Requires-Dist: scipy (>=1)
Requires-Dist: sqlparse (>=0.4.1,<0.5.0)
